{
  "menu": [
    {
      "url": "/dashboard",
      "name": "Dashboard",
      "icon": "menu-icon tf-icons bx bxs-dashboard",
      "slug": "dashboard.index"
    },
    {
      "url": "/users",
      "name": "Users",
      "icon": "menu-icon tf-icons bx bxs-user",
      "slug": "users.index"
    },
    {
      "url": "/roles",
      "name": "Roles",
      "icon": "menu-icon tf-icons bx bxs-pyramid",
      "slug": "roles.index"
    },
    {
      "name": "Settings",
      "icon": "menu-icon tf-icons bx bxs-cog",
      "slug": "settings",
      "submenu": [
        {
          "url": "/reg-settings/currency-list",
          "name": "Regional Settings",
          "slug": "regional settings",
          "submenu": [
            {
              "url": "/reg-settings/currencies",
              "name": "Currencies",
              "slug": "currencies.index"
            },
            {
              "url": "/reg-settings/vat-rates",
              "name": "VAT Rate",
              "slug": "vat-rates.index"
            },
            {
              "url": "/reg-settings/units",
              "name": "Units",
              "slug": "units.index"
            }
          ]
        },
        {
          "url": "/machines-operations",
          "name": "Machines/Operations",
          "slug": "machines-operations.index"
        },
        {
          "url": "/api-keys",
          "name": "API Keys",
          "slug": "api-keys.index"
        },
        {
          "url": "/tags",
          "name": "Tags",
          "slug": "tags.index"
        },
        {
          "url": "/additional-fields",
          "name": "Additional Fields",
          "slug": "additional-fields.index"
        },
        {
          "url": "/clients",
          "name": "Clients",
          "slug": "clients.index"
        }
      ]
    },
    {
      "url": "/clock-history",
      "name": "Clock-in/Clock-out History",
      "icon": "menu-icon tf-icons bx bxs-time-five",
      "slug": "clock-history.index"
    },
    {
      "url": "/clock-in-out",
      "name": "Clock-IN/OUT",
      "icon": "menu-icon tf-icons bx bxs-timer",
      "slug": "/clock-in-out"
    },
    {
      "url": "/user-dashboard",
      "name": "User dashboard",
      "icon": "menu-icon tf-icons bx bxs-dashboard",
      "slug": "/user-dashboard"
    }
  ]
}
